README.md
setup.py
helper_funcs/__init__.py
helper_funcs/helper_funcs.py
helper_funcs.egg-info/PKG-INFO
helper_funcs.egg-info/SOURCES.txt
helper_funcs.egg-info/dependency_links.txt
helper_funcs.egg-info/requires.txt
helper_funcs.egg-info/top_level.txt