Metadata-Version: 2.1
Name: helper-funcs
Version: 0.1.35
Summary: This module provides a handful of functions to simplify the typical data processing operations and simplifying data verification procedures.
Home-page: https://github.com/v-popov/helper_funcs
Author: Victor Popov
Author-email: victorvtf@gmail.com
License: MIT
Download-URL: https://github.com/v-popov/helper_funcs/archive/v_0_1_35.tar.gz
Keywords: Helper,Functions,Data Science
Platform: UNKNOWN
Classifier: Development Status :: 4 - Beta
Classifier: Intended Audience :: Developers
Classifier: Topic :: Software Development :: Build Tools
Classifier: License :: OSI Approved :: MIT License
Classifier: Programming Language :: Python :: 3.6
